pygsheet/drive_manager.py
pygsheet/pygsheet.py
pygsheet-0.1.19b24.dist-info/DESCRIPTION.rst
pygsheet-0.1.19b24.dist-info/METADATA
pygsheet-0.1.19b24.dist-info/RECORD
pygsheet-0.1.19b24.dist-info/WHEEL
pygsheet-0.1.19b24.dist-info/metadata.json
pygsheet-0.1.19b24.dist-info/top_level.txt
